{
  "symbol": "USD/CHF",
  "name": "US Dollar vs Swiss Franc",
  "nameCn": "美元/瑞郎",
  "timestamp": "2025-11-19T09:45:18.165Z",
  "price": {
    "close": "0.80137998",
    "high": "0.80150998",
    "low": "0.79970002",
    "open": "0.80014002",
    "change": "0.15",
    "datetime": "2025-11-19 20:00:00"
  },
  "indicators": {
    "rsi": 67.93677,
    "macd": 0.0009496469,
    "macd_signal": 0.00098565618,
    "sma20": 0.799563
  },
  "analysis": {
    "zh": {
      "title": "美元/瑞郎技术分析：[震荡整理中]",
      "content": "当前美元/瑞郎在0.7997至0.8015区间内震荡整理，短期内没有明确的趋势方向。虽然价格略有上涨，但整体波动幅度较小，市场情绪谨慎。投资者需密切关注接下来的经济数据发布，以判断未来的价格走势。\n\n技术指标方面，当前RSI值尚未提供，但一般而言，RSI在40至60区间内表明市场处于震荡状态。MACD显示出微弱的正值，表明短期内买方稍占优势。结合20日简单移动平均线（SMA），当前价格在其上方，显示出一定的支撑效应。\n\n支撑位方面，0.7995是一个重要的支撑区域，若价格跌破此水平，可能引发进一步回调。而阻力位则在0.8020附近，突破该位置有望引发更强的上涨动能。整体来看，投资者可以在支撑位附近寻找买入机会，同时在阻力位附近考虑卖出。\n\n建议交易者保持观望，待价格突破关键支撑或阻力位后再做进一步决策。在当前震荡市中，谨慎操作，控制风险，确保资金安全尤为重要。"
    },
    "en": {
      "title": "US Dollar vs Swiss Franc Technical Analysis",
      "content": "The USD/CHF pair is currently trading at 0.80138, showing a slight upward movement of 0.15% over the last 24 hours. This modest increase indicates a potential bullish sentiment in the market, especially given the recent price action which bounced off the lower range of 0.7997. The current price is also above the 20-period Simple Moving Average (SMA) of 0.79956, supporting the possibility of a continuation of the upward trend. Traders should monitor this level closely for signs of strength or weakness.\n\nIn terms of momentum indicators, the MACD is positive at 0.00095, suggesting that the bulls are gaining control. However, the lack of an RSI value prevents a full assessment of overbought or oversold conditions. Traders should be cautious, as the absence of the RSI leaves open the potential for sudden reversals. It would be prudent to wait for further confirmation from the indicators before committing to a significant position.\n\nSupport and resistance levels are crucial for gauging potential price movements. Immediate support is seen at 0.7997, while resistance can be identified near the recent high of 0.8015. A breakout above this resistance could lead to further gains, potentially targeting higher levels. Conversely, a drop below the support level may signal a bearish reversal, prompting traders to consider short positions or protective measures.\n\nFor trading strategies, a cautious approach is recommended. Traders could look to enter long positions if the price breaks above 0.8015, with a stop-loss below 0.7997 to manage risk. Alternatively, if a bearish reversal occurs, short positions could be considered below the support level, with a target set at the next significant support level. Monitoring the market closely for developments in the indicators will be essential for informed trading decisions."
    }
  }
}